bluer_geo/README.py
bluer_geo/__init__.py
bluer_geo/__main__.py
bluer_geo/config.env
bluer_geo/env.py
bluer_geo/functions.py
bluer_geo/host.py
bluer_geo/notebooks.py
bluer_geo/sample.env
bluer_geo/urls.py
bluer_geo/.abcli/QGIS.sh
bluer_geo/.abcli/abcli.sh
bluer_geo/.abcli/actions.sh
bluer_geo/.abcli/aka.sh
bluer_geo/.abcli/alias.sh
bluer_geo/.abcli/blue_geo.sh
bluer_geo/.abcli/catalog.sh
bluer_geo/.abcli/datacube.sh
bluer_geo/.abcli/gdal.sh
bluer_geo/.abcli/ingest.sh
bluer_geo/.abcli/install.sh
bluer_geo/.abcli/logging.sh
bluer_geo/.abcli/watch.sh
bluer_geo/.abcli/QGIS/download.sh
bluer_geo/.abcli/QGIS/expressions.sh
bluer_geo/.abcli/QGIS/seed.sh
bluer_geo/.abcli/QGIS/server.sh
bluer_geo/.abcli/QGIS/templates.sh
bluer_geo/.abcli/QGIS/upload.sh
bluer_geo/.abcli/catalog/browse.sh
bluer_geo/.abcli/catalog/get.sh
bluer_geo/.abcli/catalog/list.sh
bluer_geo/.abcli/catalog/query.sh
bluer_geo/.abcli/catalog/query/ingest.sh
bluer_geo/.abcli/catalog/query/label.sh
bluer_geo/.abcli/catalog/query/read.sh
bluer_geo/.abcli/datacube/crop.sh
bluer_geo/.abcli/datacube/generate.sh
bluer_geo/.abcli/datacube/get.sh
bluer_geo/.abcli/datacube/ingest.sh
bluer_geo/.abcli/datacube/label.sh
bluer_geo/.abcli/datacube/list.sh
bluer_geo/.abcli/gdal/get_crs.sh
bluer_geo/.abcli/gdal/install.sh
bluer_geo/.abcli/gdal/version.sh
bluer_geo/.abcli/tests/README.sh
bluer_geo/.abcli/tests/catalog_browse.sh
bluer_geo/.abcli/tests/catalog_list.sh
bluer_geo/.abcli/tests/catalog_query.sh
bluer_geo/.abcli/tests/catalog_query_ingest.sh
bluer_geo/.abcli/tests/datacube_crop.sh
bluer_geo/.abcli/tests/datacube_generate.sh
bluer_geo/.abcli/tests/datacube_get.sh
bluer_geo/.abcli/tests/datacube_label.sh
bluer_geo/.abcli/tests/datacube_list.sh
bluer_geo/.abcli/tests/gdal_get_crs.sh
bluer_geo/.abcli/tests/help.sh
bluer_geo/.abcli/tests/ingest.sh
bluer_geo/.abcli/tests/logging.sh
bluer_geo/.abcli/tests/seed_QGIS.sh
bluer_geo/.abcli/tests/version.sh
bluer_geo/.abcli/tests/watch.sh
bluer_geo/.abcli/tests/watch_query.sh
bluer_geo-5.99.1.dist-info/licenses/LICENSE
bluer_geo-5.99.1.dist-info/METADATA
bluer_geo-5.99.1.dist-info/WHEEL
bluer_geo-5.99.1.dist-info/top_level.txt
bluer_geo-5.99.1.dist-info/RECORD
