Metadata-Version: 2.4
Name: bluer_geo
Version: 5.99.1
Summary: 🌐 AI for a Blue Planet.
Home-page: https://github.com/kamangir/bluer-geo
Author: Arash Abadpour (Kamangir)
Author-email: arash.abadpour@gmail.com
License: CC0-1.0
Classifier: Programming Language :: Python :: 3
Classifier: Programming Language :: Unix Shell
Classifier: Operating System :: OS Independent
License-File: LICENSE
Requires-Dist: bluer_ai
Requires-Dist: bluer_flow
Requires-Dist: boto3
Requires-Dist: opencv-python
Requires-Dist: shapely!=2.0.7
Requires-Dist: folium
Requires-Dist: geojson
Requires-Dist: geopandas
Requires-Dist: rasterio
Requires-Dist: pystac-client
Dynamic: author
Dynamic: author-email
Dynamic: classifier
Dynamic: description
Dynamic: description-content-type
Dynamic: home-page
Dynamic: license
Dynamic: license-file
Dynamic: requires-dist
Dynamic: summary
